<?xml version="1.0" encoding="utf-8" ?><dwsync><file name="model.column.js" server="sites.treestar.com//var/www/dev.fluorish.com/view_designs/" local="3457534335" remote="-4611949193385883265" Dst="-1" /><file name="model.defaults.columns.js" server="sites.treestar.com//var/www/dev.fluorish.com/view_designs/" local="3457534336" remote="-4611949193385883264" Dst="-1" /><file name="model.defaults.js" server="sites.treestar.com//var/www/dev.fluorish.com/view_designs/" local="3457534336" remote="-4611949193385883264" Dst="-1" /><file name="model.ext.js" server="sites.treestar.com//var/www/dev.fluorish.com/view_designs/" local="3457534336" remote="-4611949193385883264" Dst="-1" /><file name="model.row.js" server="sites.treestar.com//var/www/dev.fluorish.com/view_designs/" local="3457534336" remote="-4611949193385883264" Dst="-1" /><file name="model.search.js" server="sites.treestar.com//var/www/dev.fluorish.com/view_designs/" local="3457534336" remote="-4611949193385883264" Dst="-1" /><file name="model.settings.js" server="sites.treestar.com//var/www/dev.fluorish.com/view_designs/" local="3457534337" remote="-4611949193385883263" Dst="-1" /><file name="model.column.js" server="sites.treestar.com//var/www/dev.fluorish.com/" local="3457534335" remote="-4611880130307957767" Dst="-1" /><file name="model.defaults.columns.js" server="sites.treestar.com//var/www/dev.fluorish.com/" local="3457534336" remote="-4611880130307957767" Dst="-1" /><file name="model.defaults.js" server="sites.treestar.com//var/www/dev.fluorish.com/" local="3457534336" remote="-4611880130307957767" Dst="-1" /><file name="model.ext.js" server="sites.treestar.com//var/www/dev.fluorish.com/" local="3457534336" remote="-4611880130307957767" Dst="-1" /><file name="model.row.js" server="sites.treestar.com//var/www/dev.fluorish.com/" local="3457534336" remote="-4611880130307957767" Dst="-1" /><file name="model.search.js" server="sites.treestar.com//var/www/dev.fluorish.com/" local="3457534336" remote="-4611880130307957766" Dst="-1" /><file name="model.settings.js" server="sites.treestar.com//var/www/dev.fluorish.com/" local="3457534337" remote="-4611880130307957766" Dst="-1" /></dwsync>