<?xml version="1.0" encoding="utf-8" ?><dwsync><file name="dom_sort.html" server="sites.treestar.com//var/www/dev.fluorish.com/view_designs/" local="3457534207" remote="-4611926103641700097" Dst="-1" /><file name="html_sort.html" server="sites.treestar.com//var/www/dev.fluorish.com/view_designs/" local="3457534207" remote="-4611926103641700097" Dst="-1" /><file name="paging_plugin.html" server="sites.treestar.com//var/www/dev.fluorish.com/view_designs/" local="3457534208" remote="-4611926103641700096" Dst="-1" /><file name="plugin_api.html" server="sites.treestar.com//var/www/dev.fluorish.com/view_designs/" local="3457534208" remote="-4611926103641700096" Dst="-1" /><file name="range_filtering.html" server="sites.treestar.com//var/www/dev.fluorish.com/view_designs/" local="3457534208" remote="-4611926103641700096" Dst="-1" /><file name="sorting_plugin.html" server="sites.treestar.com//var/www/dev.fluorish.com/view_designs/" local="3457534208" remote="-4611926103641700096" Dst="-1" /><file name="sorting_sType.html" server="sites.treestar.com//var/www/dev.fluorish.com/view_designs/" local="3457534208" remote="-4611926103641700096" Dst="-1" /><file name="dom_sort.html" server="sites.treestar.com//var/www/dev.fluorish.com/" local="3457534207" remote="-4611857040563774595" Dst="-1" /><file name="html_sort.html" server="sites.treestar.com//var/www/dev.fluorish.com/" local="3457534207" remote="-4611857040563774594" Dst="-1" /><file name="paging_plugin.html" server="sites.treestar.com//var/www/dev.fluorish.com/" local="3457534208" remote="-4611857040563774594" Dst="-1" /><file name="plugin_api.html" server="sites.treestar.com//var/www/dev.fluorish.com/" local="3457534208" remote="-4611857040563774594" Dst="-1" /><file name="range_filtering.html" server="sites.treestar.com//var/www/dev.fluorish.com/" local="3457534208" remote="-4611857040563774594" Dst="-1" /><file name="sorting_plugin.html" server="sites.treestar.com//var/www/dev.fluorish.com/" local="3457534208" remote="-4611857040563774594" Dst="-1" /><file name="sorting_sType.html" server="sites.treestar.com//var/www/dev.fluorish.com/" local="3457534208" remote="-4611857040563774594" Dst="-1" /></dwsync>